[
    {
        "card_id": 1,
        "card_title": "Morph",
        "ani_idx": 1,
        "zh_title": "变形",
        "NR_tag": "Similarity",
        "TE_tag": "Contrast Cut",
        "EL_tag": "vis elements",
        "eg_title": "The Fallen of World War II",
        "eg_source": "Finantial Times",
        "eg_url": "http://www.fallen.io/ww2/",
        "eg_year": 2013,
        "eg_category": "Social Sciences",
        "eg_subcategory": "War"
    },
    {
        "card_id": 2,
        "card_title": "Tilt & Pan",
        "ani_idx": 5,
        "zh_title": "镜头摇移",
        "NR_tag": "Similarity",
        "TE_tag": "Morph",
        "EL_tag": "Camera",
        "eg_title": "The Swing State of Swing States",
        "eg_source": "New York Times",
        "eg_url": "https://www.nytimes.com/video/us/politics/100000001883681/the-swing-state-of-swing-states.html",
        "eg_year": 2012,
        "eg_category": "Social Sciences",
        "eg_subcategory": "Politics"
    },
    {
        "card_id": 3,
        "card_title": "Cut on Action",
        "zh_title": "动作剪辑",
        "ani_idx": 4,
        "NR_tag": "Similarity",
        "DO_tag": {"Dimension Walk": 3},
        "TE_tag": "Graphics Match Cut",
        "EL_tag": "vis elements",
        "eg_title": "The Numbers Game: The Paradox of Household Income",
        "eg_source": "PolicyEd",
        "eg_url": "https://www.youtube.com/watch?v=1DU2IT8rl6c&list=WL&index=3",
        "eg_year": 2018,
        "eg_category": "Social Sciences",
        "eg_subcategory": "Economics"
    },
    {
        "card_id": 4,
        "card_title": "Match Cut",
        "zh_title": "匹配剪辑",
        "ani_idx": 3,
        "NR_tag": "Similarity",
        "DO_tag": {"Dimension Walk": 3},
        "TE_tag": "Cut on Action(vis element)",
        "EL_tag": "vis elements",
        "eg_title": "The Numbers Game: The Paradox of Household Income",
        "eg_source": "PolicyEd",
        "eg_url": "https://www.youtube.com/watch?v=1DU2IT8rl6c&list=WL&index=4",
        "eg_year": 2018,
        "eg_category": "Social Sciences",
        "eg_subcategory": "Economics"
    },
    {
        "card_id": 5,
        "card_title": "Morph",
        "zh_title": "变形",
        "ani_idx": 1,
        "NR_tag": "Contrast",
        "TE_tag": "Cut on Action(vis element)",
        "EL_tag": "vis elements",
        "eg_title": "The bad map we see every presidential election",
        "eg_source": "Vox",
        "eg_url": "https://www.youtube.com/watch?v=hlQE4IGFc5A",
        "eg_year": 2016,
        "eg_category": "Social Sciences",
        "eg_subcategory": "Politics"
    },
    {
        "card_id": 6,
        "card_title": "Tilt & Pan",
        "zh_title": "镜头摇移",
        "ani_idx": 5,
        "NR_tag": "Contrast",
        "TE_tag": "Flashback",
        "EL_tag": "vis elements",
        "eg_title": "https://www.youtube.com/watch?v=qaPQN0aW47I",
        "eg_source": "Vox",
        "eg_url": "https://www.youtube.com/watch?v=qaPQN0aW47I",
        "eg_year": 2019,
        "eg_category": "Social Sciences",
        "eg_subcategory": "Politics"
    },
    {
        "card_id": 7,
        "card_title": "Cut on Action",
        "ani_idx": 4,
        "zh_title": "动作剪辑",
        "NR_tag": "Contrast",
        "TE_tag": "Cut on Action(auxiliary element)",
        "EL_tag": "auxiliary elements",
        "eg_title": "BP US Energy Outlook 2030: America's Energy Future - 2013 Report",
        "eg_source": "bp",
        "eg_url": "https://www.youtube.com/watch?v=PN6Nq_hpUck",
        "eg_year": 2013,
        "eg_category": "Social Sciences",
        "eg_subcategory": "Energy"
    },
    {
        "card_id": 8,
        "card_title": "Match Cut",
        "zh_title": "匹配剪辑",
        "ani_idx": 3,
        "NR_tag": "Contrast",
        "TE_tag": "Contrast Cut",
        "EL_tag": "visualization",
        "eg_title": "Donald Trump's $20 Trillion Problem",
        "eg_source": "Visual Capitalist",
        "eg_url": "https://www.youtube.com/watch?v=tgpfswDHA_Y",
        "eg_year": 2017,
        "eg_category": "Social Sciences",
        "eg_subcategory": "Politics"
    },
    {
        "card_id": 9,
        "card_title": "Lap Dissolve",
        "zh_title": "叠化",
        "ani_idx": 2,
        "NR_tag": "Contrast",
        "TE_tag": "Establishing Shot",
        "EL_tag": "Visualization",
        "eg_title": "China's fight with the NBA, explained",
        "eg_source": "Vox",
        "eg_url": "https://www.youtube.com/watch?v=GHpFjtuAYLQ",
        "eg_year": 2019,
        "eg_category": "Social Sciences",
        "eg_subcategory": "Sports"
    },
    {
        "card_id": 10,
        "card_title": "Morph",
        "zh_title": "变形",
        "ani_idx": 1,
        "NR_tag": "Contrast",
        "TE_tag": "Lap dissolve",
        "EL_tag": "Visualization",
        "eg_title": "The Electoral College, explained",
        "eg_source": "Vox",
        "eg_url": "https://www.youtube.com/watch?v=ajavsMbCapY",
        "eg_year": 2020,
        "eg_category": "Social Sciences",
        "eg_subcategory": "Politics"
    },
    {
        "card_id": 11,
        "card_title": "Cut on Action",
        "zh_title": "动作剪辑",
        "ani_idx": 4,
        "NR_tag": "Contrast",
        "TE_tag": "Morph",
        "EL_tag": "vis elements",
        "eg_title": "The bad map we see every presidential election",
        "eg_source": "Vox",
        "eg_url": "https://www.youtube.com/watch?v=hlQE4IGFc5A",
        "eg_year": 2016,
        "eg_category": "Social Sciences",
        "eg_subcategory": "Politics"
    },
    {
        "card_id": 12,
        "card_title": "Match Cut",
        "zh_title": "匹配剪辑",
        "ani_idx": 3,
        "NR_tag": "Elaboration",
        "TE_tag": "Cut on Action(vis element)",
        "EL_tag": "Embelishment",
        "eg_title": "Who pays the lowest taxes in the US?",
        "eg_source": "Vox",
        "eg_url": "https://www.youtube.com/watch?v=kXCGbAv8YPw",
        "eg_year": 2019,
        "eg_category": "Social Sciences",
        "eg_subcategory": "Economics"
    },
    {
        "card_id": 13,
        "card_title": "Lap Dissolve",
        "zh_title": "叠化",
        "ani_idx": 2,
        "NR_tag": "Elaboration",
        "TE_tag": "Insert Shot",
        "EL_tag": "Visualization",
        "eg_title": "Why are houses so expensive?",
        "eg_source": "The Guardian",
        "eg_url": "https://www.youtube.com/watch?v=vhAXp0xzMFg",
        "eg_year": 2019,
        "eg_category": "Social Sciences",
        "eg_subcategory": "Economics"
    },
    {
        "card_id": 14,
        "card_title": "Insert Shot",
        "zh_title": "特写镜头",
        "ani_idx": 6,
        "NR_tag": "Elaboration",
        "TE_tag": "Invisible Cut",
        "EL_tag": "camera",
        "eg_title": "The Numbers Game: Do The Rich Get All The Gains?",
        "eg_source": "PolicyEd",
        "eg_url": "https://www.youtube.com/watch?v=GcdqGUWj2oo&list=WL&index=20",
        "eg_year": 2019,
        "eg_category": "Social Sciences",
        "eg_subcategory": "Economics"
    },
    {
        "card_id": 15,
        "card_title": "Invisible Cut",
        "zh_title": "隐藏剪辑",
        "ani_idx": 7,
        "NR_tag": "Elaboration",
        "TE_tag": "Cut on Action(auxiliary element)",
        "EL_tag": "auxiliary elements",
        "eg_title": "Dewi and Putri: How Inequality Separates Two Girls from Indonesia",
        "eg_source": "World Bank",
        "eg_url": "https://www.youtube.com/watch?v=a0wHffQi4xo",
        "eg_year": 2014,
        "eg_category": "Social Sciences",
        "eg_subcategory": "politics"
    },
    {
        "card_id": 16,
        "card_title": "Insert Shot",
        "zh_title": "特写镜头",
        "ani_idx": 6,
        "NR_tag": "Elaboration",
        "TE_tag": "Graphics Match Cut",
        "EL_tag": "vis elements",
        "eg_title": "Why are some people left-handed? - Daniel M. Abrams",
        "eg_source": "TED-Ed",
        "eg_url": "https://www.youtube.com/watch?v=TGLYcYCm2FM",
        "eg_year": 2015,
        "eg_category": "Biology",
        "eg_subcategory": "Human"
    },
    {
        "card_id": 17,
        "card_title": "Cut on Action",
        "zh_title": "动作剪辑",
        "ani_idx": 4,
        "NR_tag": "Generalization",
        "TE_tag": "Establishing Shot",
        "EL_tag": "Embelishment",
        "eg_title": "The Mind-Boggling Numbers Behind the Super Bowl | NFL Infographic",
        "eg_source": "NFL",
        "eg_url": "https://www.youtube.com/watch?v=BhBX9r4gJzY",
        "eg_year": 2016,
        "eg_category": "Social Sciences",
        "eg_subcategory": "Sports"
    },
    {
        "card_id": 18,
        "card_title": "Establishing Shot",
        "zh_title": "定场镜头",
        "ani_idx": 8,
        "NR_tag": "Generalization",
        "TE_tag": "Cut on Action(auxiliary element)",
        "EL_tag": "Camera",
        "eg_title": "Inequality: How Wealth is Distributed in the UK",
        "eg_source": "The Guardian",
        "eg_url": "https://www.theguardian.com/commentisfree/video/2013/oct/08/inequality-how-wealth-distributed-uk-animated-video",
        "eg_year": 2013,
        "eg_category": "Social Sciences",
        "eg_subcategory": "Economics"
    },
    {
        "card_id": 19,
        "card_title": "Cut on Action",
        "zh_title": "动作剪辑",
        "ani_idx": 4,
        "NR_tag": "Generalization",
        "TE_tag": "Cut on Action(vis element)",
        "EL_tag": "vis elements",
        "eg_title": "The bad map we see every presidential election",
        "eg_source": "Vox",
        "eg_url": "https://www.youtube.com/watch?v=hlQE4IGFc5A",
        "eg_year": 2016,
        "eg_category": "Social Sciences",
        "eg_subcategory": "Politics"
    },
    {
        "card_id": 20,
        "card_title": "Lap Dissolve",
        "zh_title": "叠化",
        "ani_idx": 2,
        "NR_tag": "Generalization",
        "TE_tag": "Crane shot",
        "EL_tag": "Visualization",
        "eg_title": "Visualizing the Structure of the World Economy and Population in One Chart",
        "eg_source": "World Bank",
        "eg_url": "https://www.youtube.com/watch?v=CRfc85AIH3c",
        "eg_year": 2015,
        "eg_category": "Social Sciences",
        "eg_subcategory": "Economics"
    },
    {
        "card_id": 21,
        "card_title": "Establishing Shot",
        "zh_title": "定场镜头",
        "ani_idx": 8,
        "NR_tag": "Cause-Effect",
        "TE_tag": "Cut on Action(vis element)",
        "EL_tag": "vis elements",
        "eg_title": "Inequality: How Wealth is Distributed in the UK",
        "eg_source": "The Guardian",
        "eg_url": "https://www.theguardian.com/commentisfree/video/2013/oct/08/inequality-how-wealth-distributed-uk-animated-video",
        "eg_year": 2013,
        "eg_category": "Social Sciences",
        "eg_subcategory": "Economics"
    },
    {
        "card_id": 22,
        "card_title": "Establishing Shot",
        "zh_title": "定场镜头",
        "ani_idx": 8,
        "NR_tag": "Cause-Effect",
        "DO_tag": {"Dimension Walk": 1},
        "TE_tag": "Match on Action",
        "EL_tag": "Camera",
        "eg_title": "Watch This: An Infographic Exploration of Online Video",
        "eg_source": "shutterstock",
        "eg_url": "https://www.shutterstock.com/blog/an-infographic-exploration-of-online-video",
        "eg_year": 2014,
        "eg_category": "Social Sciences",
        "eg_subcategory": "Health"
    },
    {
        "card_id": 23,
        "card_title": "Cut on Action",
        "zh_title": "动作剪辑",
        "ani_idx": 4,
        "NR_tag": "Sequence",
        "TE_tag": "Jump Cut",
        "EL_tag": "timeline",
        "eg_title": "America's presidential primaries, explained",
        "eg_source": "Vox",
        "eg_url": "https://www.youtube.com/watch?v=tCvMtkEVqdA",
        "eg_year": 2020,
        "eg_category": "Social Sciences",
        "eg_subcategory": "Politics"
    },
    {
        "card_id": 24,
        "card_title": "Match Cut",
        "zh_title": "匹配剪辑",
        "ani_idx": 3,
        "NR_tag": "Sequence",
        "TE_tag": "Progressive Cut",
        "EL_tag": "Embelishment",
        "eg_title": "人口过剩-解释人口大爆炸",
        "eg_source": "Kurzgesagt – In a Nutshell",
        "eg_url": "https://www.youtube.com/watch?v=QsBT5EQt348",
        "eg_year": 2016,
        "eg_category": "Social Sciences",
        "eg_subcategory": "Health"
    },
    {
        "card_id": 25,
        "card_title": "Morph",
        "zh_title": "变形",
        "ani_idx": 1,
        "NR_tag": "Sequence",
        "TE_tag": "Jump Cut",
        "EL_tag": "timeline",
        "eg_title": "America's presidential primaries, explained",
        "eg_source": "Vox",
        "eg_url": "https://www.youtube.com/watch?v=tCvMtkEVqdA",
        "eg_year": 2020,
        "eg_category": "Social Sciences",
        "eg_subcategory": "Politics"
    },
    {
        "card_id": 26,
        "card_title": "Cut on Action",
        "zh_title": "动作剪辑",
        "NR_tag": "Sequence",
        "ani_idx": 4,
        "TE_tag": "Progressive Cut",
        "EL_tag": "Embelishment",
        "eg_title": "How Africa could one day rival China | The Economist",
        "eg_source": "The Economist",
        "eg_url": "https://www.youtube.com/watch?v=p8fl-u1UMVA",
        "eg_year": 2020,
        "eg_category": "Social Sciences",
        "eg_subcategory": "Economics"
    }
]